hidiocore/__init__.py
hidiocore/client/__init__.py
hidiocore/schema/__init__.py
hidiocore/schema/common.capnp
hidiocore/schema/devicefunction.capnp
hidiocore/schema/hidio.capnp
hidiocore/schema/hidiowatcher.capnp
hidiocore/schema/hostmacro.capnp
hidiocore/schema/usbkeyboard.capnp
hidiocore-0.1.0b3.dist-info/WHEEL
hidiocore-0.1.0b3.dist-info/METADATA
hidiocore-0.1.0b3.dist-info/RECORD
