Metadata-Version: 2.1
Name: hidiocore
Version: 0.1.0b3
Summary: HID-IO Python Library
Home-page: http://hid-io.com
License: UNKNOWN
Author: Jacob Alexander
Author-email: haata@kiibohd.com
Requires-Python: >=3.7
Classifier: Topic :: Software Development :: Libraries
Classifier: Intended Audience :: Developers
Classifier: Programming Language :: Python :: 3
Requires-Dist: cython>=0.29
Requires-Dist: pycapnp-async>=0.7
Requires-Dist: pygtail>=0.11.1
